pyverbplt.py
pyverbplt-24.9.dist-info/LICENSE
pyverbplt-24.9.dist-info/METADATA
pyverbplt-24.9.dist-info/WHEEL
pyverbplt-24.9.dist-info/top_level.txt
pyverbplt-24.9.dist-info/RECORD
