Metadata-Version: 2.1
Name: pyverbplt
Version: 24.9
Summary: Python library designed to load `.plt` files, created by the Versatile Electron Radiation Belts (VERB) code
Home-page: https://github.com/radiation-belts/pyverbplt
Author: Alexander Drozdov
Author-email: adrozdov@ucla.edu
Classifier: Programming Language :: Python :: 3
Classifier: License :: OSI Approved :: BSD License
Classifier: Operating System :: OS Independent
Requires-Python: >=3.9
License-File: LICENSE
Requires-Dist: numpy
